gdemandfcast/.ipynb_checkpoints/Untitled-checkpoint.ipynb
gdemandfcast/.ipynb_checkpoints/ai-checkpoint.py
gdemandfcast/.ipynb_checkpoints/example-checkpoint.py
gdemandfcast/__init__.py
gdemandfcast/ai.py
gdemandfcast/data/Test Data.xlsx
gdemandfcast/data/Train Data.xlsx
gdemandfcast/py.typed
gdemandfcast-0.6.59.dist-info/LICENSE
gdemandfcast-0.6.59.dist-info/WHEEL
gdemandfcast-0.6.59.dist-info/METADATA
gdemandfcast-0.6.59.dist-info/RECORD
