Metadata-Version: 2.1
Name: gdemandfcast
Version: 0.6.59
Summary: Generic Python Package for Time Series Forecasting.
Home-page: https://github.com/altcp/gdemandfcast
License: GNU GPL v3.0
Keywords: Time Series,Deep Learning,Machine Learning
Author: altcp
Author-email: colab.tcp@gmail.com
Requires-Python: >=3.8,<3.11
Classifier: Development Status :: 4 - Beta
Classifier: Intended Audience :: Developers
Classifier: License :: OSI Approved :: GNU General Public License v3 or later (GPLv3+)
Classifier: License :: Other/Proprietary License
Classifier: Operating System :: OS Independent
Classifier: Programming Language :: Python :: 3
Classifier: Programming Language :: Python :: 3.8
Classifier: Programming Language :: Python :: 3.9
Classifier: Topic :: Software Development :: Libraries :: Python Modules
Requires-Dist: ESRNN (>=0.1.3,<0.2.0)
Requires-Dist: keras-tuner (>=1.0.3,<2.0.0)
Requires-Dist: matplotlib (>=3.4.2,<4.0.0)
Requires-Dist: numpy (==1.19.5)
Requires-Dist: openpyxl (>=3.0.7,<4.0.0)
Requires-Dist: pandas (>=1.3.1,<2.0.0)
Requires-Dist: pmdarima (>=1.8.2,<2.0.0)
Requires-Dist: scikit-learn (>=0.24.2,<0.25.0)
Requires-Dist: seaborn (>=0.11.2,<0.12.0)
Requires-Dist: tensorflow (==2.5.1)
Requires-Dist: tensorflow-probability (>=0.13.0,<0.14.0)
Requires-Dist: xgboost (>=1.4.2,<2.0.0)
Project-URL: Repository, https://github.com/altcp/gdemandfcast
